README.md
setup.py
shopee_api/__init__.py
shopee_api/settings.py
shopee_api/utils/__init__.py
shopee_api/utils/product_url.py
shopee_api/utils/urls.py
shopee_api/utils/__init__.py
shopee_api/utils/product_url.py
shopee_api/utils/urls.py
shopee_api_wrapper.egg-info/PKG-INFO
shopee_api_wrapper.egg-info/SOURCES.txt
shopee_api_wrapper.egg-info/dependency_links.txt
shopee_api_wrapper.egg-info/top_level.txt