Metadata-Version: 2.1
Name: shopee-api-wrapper
Version: 0.2.1
Summary: A simple library that communicates with the Shopee website API.
Author:  Marcuth
Author-email: example@gmail.com
License: MIT License
Keywords: shopee api crawler scraper product shop
